odoo8_addon_l10n_ch_fds_upload_sepa-8.0.1.0.1.99.dev22-py2.7-nspkg.pth
odoo8_addon_l10n_ch_fds_upload_sepa-8.0.1.0.1.99.dev22.dist-info/METADATA
odoo8_addon_l10n_ch_fds_upload_sepa-8.0.1.0.1.99.dev22.dist-info/RECORD
odoo8_addon_l10n_ch_fds_upload_sepa-8.0.1.0.1.99.dev22.dist-info/WHEEL
odoo8_addon_l10n_ch_fds_upload_sepa-8.0.1.0.1.99.dev22.dist-info/namespace_packages.txt
odoo8_addon_l10n_ch_fds_upload_sepa-8.0.1.0.1.99.dev22.dist-info/top_level.txt
odoo_addons/l10n_ch_fds_upload_sepa/README.rst
odoo_addons/l10n_ch_fds_upload_sepa/__init__.py
odoo_addons/l10n_ch_fds_upload_sepa/__openerp__.py
odoo_addons/l10n_ch_fds_upload_sepa/i18n/am.po
odoo_addons/l10n_ch_fds_upload_sepa/i18n/ar.po
odoo_addons/l10n_ch_fds_upload_sepa/i18n/bg.po
odoo_addons/l10n_ch_fds_upload_sepa/i18n/bs.po
odoo_addons/l10n_ch_fds_upload_sepa/i18n/ca.po
odoo_addons/l10n_ch_fds_upload_sepa/i18n/ca_ES.po
odoo_addons/l10n_ch_fds_upload_sepa/i18n/cs.po
odoo_addons/l10n_ch_fds_upload_sepa/i18n/da.po
odoo_addons/l10n_ch_fds_upload_sepa/i18n/de.po
odoo_addons/l10n_ch_fds_upload_sepa/i18n/el_GR.po
odoo_addons/l10n_ch_fds_upload_sepa/i18n/en_AU.po
odoo_addons/l10n_ch_fds_upload_sepa/i18n/en_GB.po
odoo_addons/l10n_ch_fds_upload_sepa/i18n/es.po
odoo_addons/l10n_ch_fds_upload_sepa/i18n/es_AR.po
odoo_addons/l10n_ch_fds_upload_sepa/i18n/es_CL.po
odoo_addons/l10n_ch_fds_upload_sepa/i18n/es_CO.po
odoo_addons/l10n_ch_fds_upload_sepa/i18n/es_CR.po
odoo_addons/l10n_ch_fds_upload_sepa/i18n/es_DO.po
odoo_addons/l10n_ch_fds_upload_sepa/i18n/es_EC.po
odoo_addons/l10n_ch_fds_upload_sepa/i18n/es_MX.po
odoo_addons/l10n_ch_fds_upload_sepa/i18n/es_PE.po
odoo_addons/l10n_ch_fds_upload_sepa/i18n/es_PY.po
odoo_addons/l10n_ch_fds_upload_sepa/i18n/es_VE.po
odoo_addons/l10n_ch_fds_upload_sepa/i18n/et.po
odoo_addons/l10n_ch_fds_upload_sepa/i18n/eu.po
odoo_addons/l10n_ch_fds_upload_sepa/i18n/fa.po
odoo_addons/l10n_ch_fds_upload_sepa/i18n/fi.po
odoo_addons/l10n_ch_fds_upload_sepa/i18n/fr.po
odoo_addons/l10n_ch_fds_upload_sepa/i18n/fr_CA.po
odoo_addons/l10n_ch_fds_upload_sepa/i18n/fr_CH.po
odoo_addons/l10n_ch_fds_upload_sepa/i18n/fr_FR.po
odoo_addons/l10n_ch_fds_upload_sepa/i18n/gl.po
odoo_addons/l10n_ch_fds_upload_sepa/i18n/gl_ES.po
odoo_addons/l10n_ch_fds_upload_sepa/i18n/he.po
odoo_addons/l10n_ch_fds_upload_sepa/i18n/hi.po
