Metadata-Version: 2.1
Name: odoo8-addon-l10n-ch-fds-upload-sepa
Version: 8.0.1.0.1.99.dev22
Summary: Upload SEPA files to FDS PostFinance
Home-page: http://www.compassion.ch/
Author: Compassion CH, Odoo Comunity Association (OCA)
Author-email: UNKNOWN
License: AGPL-3
Platform: UNKNOWN
Classifier: Programming Language :: Python
Classifier: Framework :: Odoo
Classifier: License :: OSI Approved :: GNU Affero General Public License v3
Requires-Python: ~=2.7
Requires-Dist: odoo8-addon-l10n-ch-fds-postfinance
Requires-Dist: odoo8-addon-l10n-ch-sepa
Requires-Dist: odoo (<9.0a,>=8.0a)
Requires-Dist: pysftp
